<?xml version="1.0" encoding="utf-8"?>
<LanguageData>
  <!--The following translations were generated by https://www.deepl.com/-->
  <!-- EN: morita bullet -->
  <Bullet_MoritaRifleBullet.label>balle morita</Bullet_MoritaRifleBullet.label>
  <!-- EN: (SST) Morita MK1 (Carbine) -->
  <SST_MoritaMK1CarbineGun.label>(SST) Morita MK1 (Carabine)</SST_MoritaMK1CarbineGun.label>
  <!-- EN: A cut-down version of the Morita Mk1 rifle, this carbine version is chambered in .308 and features no under barrel shotgun making it less unwieldy. This is a favorite of Officers within the Mobile Infantry, and Navy personnel. -->
  <SST_MoritaMK1CarbineGun.description>Version réduite du fusil Morita Mk1, cette carabine est chambrée en .308 et n'a pas de canon sous le fusil, ce qui la rend moins encombrante. C'est l'arme préférée des officiers de l'infanterie mobile et du personnel de la marine.</SST_MoritaMK1CarbineGun.description>
  <!-- EN: stock -->
  <SST_MoritaMK1CarbineGun.tools.stock.label>stock</SST_MoritaMK1CarbineGun.tools.stock.label>
  <!-- EN: barrel -->
  <SST_MoritaMK1CarbineGun.tools.barrel.label>tonneau</SST_MoritaMK1CarbineGun.tools.barrel.label>
  <SST_MoritaMK1CarbineGun.verbs.Verb_Shoot.label>(SST) Morita MK1 (Carabine)</SST_MoritaMK1CarbineGun.verbs.Verb_Shoot.label>
  <!-- EN: (SST) Morita Mk1 -->
  <SST_MoritaMK1Gun.label>(SST) Morita Mk1</SST_MoritaMK1Gun.label>
  <!-- EN: The standard rifle for the Federation. It's a fully automatic bullpup rifle chambered in .308 with an under barrel shotgun attached; a favorite within the Federation and standard-issue for the Mobile Infantry. Kill bugs! -->
  <SST_MoritaMK1Gun.description>Le fusil standard de la Fédération. Il s'agit d'un fusil bullpup entièrement automatique, chambré en .308, auquel est attaché un fusil à pompe sous canon.</SST_MoritaMK1Gun.description>
  <SST_MoritaMK1Gun.tools.stock.label>stock</SST_MoritaMK1Gun.tools.stock.label>
  <SST_MoritaMK1Gun.tools.barrel.label>tonneau</SST_MoritaMK1Gun.tools.barrel.label>
  <SST_MoritaMK1Gun.verbs.Verb_Shoot.label>(SST) Morita Mk1</SST_MoritaMK1Gun.verbs.Verb_Shoot.label>
  <!-- EN: (SST) Morita MK1 (Scoped) -->
  <SST_MoritaMK1ScopedGun.label>(SST) Morita MK1 (Scoped)</SST_MoritaMK1ScopedGun.label>
  <!-- EN: The standard rifle for the Federation. It is a fully automatic bullpup rifle chambered in 308. with an under barrel shotgun attached and a high powered scope, for precision bug-killing. -->
  <SST_MoritaMK1ScopedGun.description>Le fusil standard de la Fédération. Il s'agit d'un fusil bullpup entièrement automatique, chambré en 308. Il est équipé d'un fusil à pompe sous le canon et d'une lunette de visée très puissante, pour tuer des insectes avec précision.</SST_MoritaMK1ScopedGun.description>
  <SST_MoritaMK1ScopedGun.tools.stock.label>stock</SST_MoritaMK1ScopedGun.tools.stock.label>
  <SST_MoritaMK1ScopedGun.tools.barrel.label>tonneau</SST_MoritaMK1ScopedGun.tools.barrel.label>
  <SST_MoritaMK1ScopedGun.verbs.Verb_Shoot.label>(SST) Morita MK1 (Scoped)</SST_MoritaMK1ScopedGun.verbs.Verb_Shoot.label>
  <!-- EN: (SST) Morita Mk3 -->
  <SST_MoritaMK3Gun.label>(SST) Morita Mk3</SST_MoritaMK3Gun.label>
  <!-- EN: This beefed up and slightly larger version of the Morita is chambered in 10mm x 50 caseless ammunition, and wields an under barrel 30mm grenade launcher. Though it's even more unwieldy than the standard Morita, the Mk3 makes up for this with its massive punch; this is more common amongst Federal Marines, whereas the Mobile Infantry tends to stay with the Mk1. -->
  <SST_MoritaMK3Gun.description>Cette version renforcée et légèrement plus grande du Morita est équipée de munitions sans douille de 10 mm x 50 et d'un lance-grenades de 30 mm placé sous le canon. Bien qu'il soit encore plus encombrant que le Morita standard, le Mk3 le compense par sa puissance de frappe massive</SST_MoritaMK3Gun.description>
  <SST_MoritaMK3Gun.tools.stock.label>stock</SST_MoritaMK3Gun.tools.stock.label>
  <SST_MoritaMK3Gun.tools.barrel.label>tonneau</SST_MoritaMK3Gun.tools.barrel.label>
  <SST_MoritaMK3Gun.verbs.Verb_Shoot.label>(SST) Morita Mk3</SST_MoritaMK3Gun.verbs.Verb_Shoot.label>
</LanguageData>
